memetextgen/__init__.py
memetextgen/__main__.py
memetextgen/meme.py
memetextgen-0.1.0.dist-info/licenses/LICENSE
tests/__init__.py
tests/test_meme.py
memetextgen-0.1.0.dist-info/METADATA
memetextgen-0.1.0.dist-info/WHEEL
memetextgen-0.1.0.dist-info/entry_points.txt
memetextgen-0.1.0.dist-info/top_level.txt
memetextgen-0.1.0.dist-info/RECORD
